{"cameraMode":{"drawMode":0,"name":"Shaded","section":"Shading Mode"},"sceneLighting":true,"audioPlay":false,"sceneViewState":{"showFog":true,"showMaterialUpdate":false,"showSkybox":true,"showFlares":true,"showImageEffects":true,"showParticleSystems":true},"in2DMode":false,"pivot":{"x":0.4365459382534027,"y":0.6917844414710999,"z":-2.713594675064087},"rotation":{"x":0.16509753465652467,"y":-0.1053413599729538,"z":0.017812224105000497,"w":0.9805953502655029},"size":0.5192352533340454,"orthographic":false}